{
	"format_version": "1.8.0",
	"animations": {
		"animation.caster_piglin.idle": {
			"animation_length": 2.04,
			"bones": {
				"bipedRightArm": {
					"rotation": {
						"0.0": {
							"vector": [0, 0, 0]
						},
						"0.52": {
							"vector": [-2.47365, 1.5216, 1.98385],
							"easing": "easeInSine"
						},
						"1.04": {
							"vector": [-2.47, 1.52, 1.98]
						},
						"1.56": {
							"vector": [2.5, 0, 0],
							"easing": "easeInSine"
						},
						"2.04": {
							"vector": [0, 0, 0],
							"easing": "easeInSine"
						}
					}
				},
				"bipedLeftArm": {
					"rotation": {
						"0.0": {
							"vector": [0, 0, 0]
						},
						"0.52": {
							"vector": [2.5, 0, 0]
						},
						"1.04": {
							"vector": [0, 0, 0]
						},
						"1.56": {
							"vector": [0, 0, 0]
						},
						"2.04": {
							"vector": [0, 0, 0],
							"easing": "easeInSine"
						}
					},
					"position": {
						"0.0": {
							"vector": [0, 0, 0]
						},
						"0.52": {
							"vector": [0, 0.25, 0]
						},
						"1.04": {
							"vector": [0, 0, 0]
						},
						"1.56": {
							"vector": [0, -0.25, 0]
						},
						"2.04": {
							"vector": [0, 0, 0],
							"easing": "easeInSine"
						}
					}
				}
			}
		},
		"animation.caster_piglin.walk": {
			"animation_length": 1.4,
			"bones": {
				"bipedLeftLeg": {
					"rotation": {
						"0.0": {
							"vector": [0, 0, 0]
						},
						"0.32": {
							"vector": [-20, 0, 0],
							"easing": "linear"
						},
						"0.68": {
							"vector": [0, 0, 0],
							"easing": "linear"
						},
						"1.04": {
							"vector": [20, 0, 0],
							"easing": "linear"
						},
						"1.4": {
							"vector": [0, 0, 0],
							"easing": "linear"
						}
					}
				},
				"bipedRightLeg": {
					"rotation": {
						"0.0": {
							"vector": [0, 0, 0]
						},
						"0.32": {
							"vector": [20, 0, 0],
							"easing": "linear"
						},
						"0.68": {
							"vector": [0, 0, 0],
							"easing": "linear"
						},
						"1.04": {
							"vector": [-20, 0, 0],
							"easing": "linear"
						},
						"1.4": {
							"vector": [0, 0, 0],
							"easing": "linear"
						}
					}
				},
				"bipedRightArm": {
					"rotation": {
						"0.0": {
							"vector": [0, 0, 0]
						},
						"0.32": {
							"vector": [-7.5, 0, 0],
							"easing": "easeInSine"
						},
						"0.68": {
							"vector": [0, 0, 0],
							"easing": "easeInSine"
						},
						"1.04": {
							"vector": [7.5, 0, 0],
							"easing": "easeInSine"
						},
						"1.4": {
							"vector": [0, 0, 0],
							"easing": "easeInSine"
						}
					}
				},
				"bipedLeftArm": {
					"rotation": {
						"0.0": {
							"vector": [0, 0, 0]
						},
						"0.32": {
							"vector": [7.5, 0, 0]
						},
						"0.68": {
							"vector": [1, 0, 0]
						},
						"1.04": {
							"vector": [-9, 0, 0]
						},
						"1.4": {
							"vector": [0, 0, 0]
						}
					}
				},
				"bipedHead": {
					"rotation": {
						"0.0": {
							"vector": [0, 0, 0]
						},
						"0.64": {
							"vector": [2, 0, 0],
							"easing": "easeInSine"
						},
						"1.4": {
							"vector": [0, 0, 0]
						}
					}
				}
			}
		}
	},
	"geckolib_format_version": 2
}